docmind_parser_mcp/__init__.py
docmind_parser_mcp/_uri_utils.py
docmind_parser_mcp/config.py
docmind_parser_mcp/docmind_config.yaml
docmind_parser_mcp/server.py
docmind_parser_mcp/transport/sse.py
docmind_parser_mcp/transport/stdio.py
docmind_parser_mcp-0.1.4.dist-info/METADATA
docmind_parser_mcp-0.1.4.dist-info/WHEEL
docmind_parser_mcp-0.1.4.dist-info/entry_points.txt
docmind_parser_mcp-0.1.4.dist-info/licenses/LICENSE
docmind_parser_mcp-0.1.4.dist-info/RECORD
