Metadata-Version: 2.3
Name: docmind-parser-mcp
Version: 0.1.4
Summary: An MCP server for the 'docmind_parser' library.
Author-email: 足溪 <sanchuan.ssc@alibaba-inc.com>
Classifier: License :: OSI Approved :: Apache Software License
Classifier: Operating System :: OS Independent
Classifier: Programming Language :: Python :: 3
Requires-Python: <4.0,>=3.13
Requires-Dist: docmind-doc-json-sdk>=1.1.2
Requires-Dist: mcp-server>=0.1.4
Requires-Dist: numpy>=2.0
Requires-Dist: pyyaml>=6.0.2
Requires-Dist: sse-starlette>=2.3.5
Requires-Dist: typing-extensions>=4.13.2
Requires-Dist: typing-inspection>=0.4.1
Requires-Dist: uvicorn>=0.34.2
